promptflow/evals/__init__.py
promptflow/evals/_common/__init__.py
promptflow/evals/_common/constants.py
promptflow/evals/_common/rai_service.py
promptflow/evals/_common/utils.py
promptflow/evals/_constants.py
promptflow/evals/_exceptions.py
promptflow/evals/_http_utils.py
promptflow/evals/_user_agent.py
promptflow/evals/_version.py
promptflow/evals/evaluate/__init__.py
promptflow/evals/evaluate/_batch_run_client/__init__.py
promptflow/evals/evaluate/_batch_run_client/batch_run_context.py
promptflow/evals/evaluate/_batch_run_client/code_client.py
promptflow/evals/evaluate/_batch_run_client/proxy_client.py
promptflow/evals/evaluate/_eval_run.py
promptflow/evals/evaluate/_evaluate.py
promptflow/evals/evaluate/_telemetry/__init__.py
promptflow/evals/evaluate/_utils.py
promptflow/evals/evaluators/__init__.py
promptflow/evals/evaluators/_bleu/__init__.py
promptflow/evals/evaluators/_bleu/_bleu.py
promptflow/evals/evaluators/_chat/__init__.py
promptflow/evals/evaluators/_chat/_chat.py
promptflow/evals/evaluators/_chat/retrieval/__init__.py
promptflow/evals/evaluators/_chat/retrieval/_retrieval.py
promptflow/evals/evaluators/_chat/retrieval/retrieval.prompty
promptflow/evals/evaluators/_coherence/__init__.py
promptflow/evals/evaluators/_coherence/_coherence.py
promptflow/evals/evaluators/_coherence/coherence.prompty
promptflow/evals/evaluators/_content_safety/__init__.py
promptflow/evals/evaluators/_content_safety/_content_safety.py
promptflow/evals/evaluators/_content_safety/_content_safety_base.py
promptflow/evals/evaluators/_content_safety/_content_safety_chat.py
promptflow/evals/evaluators/_content_safety/_hate_unfairness.py
promptflow/evals/evaluators/_content_safety/_self_harm.py
promptflow/evals/evaluators/_content_safety/_sexual.py
promptflow/evals/evaluators/_content_safety/_violence.py
promptflow/evals/evaluators/_eci/_eci.py
promptflow/evals/evaluators/_f1_score/__init__.py
promptflow/evals/evaluators/_f1_score/_f1_score.py
promptflow_evals-0.3.5.dist-info/METADATA
promptflow_evals-0.3.5.dist-info/WHEEL
promptflow_evals-0.3.5.dist-info/RECORD
